netbox_paas/__init__.py
netbox_paas/constants.py
netbox_paas/forms.py
netbox_paas/models.py
netbox_paas/navigation.py
netbox_paas/nb_settings.py
netbox_paas/paas.py
netbox_paas/tables.py
netbox_paas/urls.py
netbox_paas/utils.py
netbox_paas/validators.py
netbox_paas/views.py
netbox_paas/api/__init__.py
netbox_paas/api/serializers.py
netbox_paas/api/urls.py
netbox_paas/api/views.py
netbox_paas/migrations/0001_initial.py
netbox_paas/migrations/0002_rename_application.py
netbox_paas/migrations/__init__.py
netbox_paas/templates/netbox_paas/netboxconfiguration.html
netbox_paas/templates/netbox_paas/netboxdbbackup.html
netbox_paas/templates/netbox_paas/nodelogs.html
netbox_paas/templates/netbox_paas/plugin_disable.html
netbox_paas/templates/netbox_paas/plugin_enable.html
netbox_paas/templates/netbox_paas/plugin_uninstall.html
netbox_paas/templates/netbox_paas/plugins_store.html
netbox_paas/templates/netbox_paas/inc/env_info.html
netbox_paas/templates/netbox_paas/inc/env_node_groups.html
netbox_paas/templates/netbox_paas/inc/plugin_store.html
netbox_paas-0.3.6.dist-info/METADATA
netbox_paas-0.3.6.dist-info/WHEEL
netbox_paas-0.3.6.dist-info/top_level.txt
netbox_paas-0.3.6.dist-info/RECORD
