Metadata-Version: 2.2
Name: netbox-paas
Version: 0.3.6
Summary: Enhances NetBox on CloudMyDC's PaaS with advanced management and control features.
Home-page: https://github.com/Onemind-Services-LLC/netbox-paas/
Download-URL: https://github.com/Onemind-Services-LLC/netbox-paas/
Author: Abhimanyu Saharan
Author-email: asaharan@onemindservices.com
Maintainer: Abhimanyu Saharan
Maintainer-email: asaharan@onemindservices.com
Keywords: netbox,netbox-plugin
Classifier: Development Status :: 3 - Alpha
Classifier: Framework :: Django
Classifier: Programming Language :: Python :: 3
Requires-Dist: py-jelastic
Requires-Dist: croniter<3.0.0
Requires-Dist: semver<4.0.0
Requires-Dist: requirements-parser
Requires-Dist: elastic-apm
Dynamic: author
Dynamic: author-email
Dynamic: classifier
Dynamic: description
Dynamic: description-content-type
Dynamic: download-url
Dynamic: home-page
Dynamic: keywords
Dynamic: maintainer
Dynamic: maintainer-email
Dynamic: requires-dist
Dynamic: summary
